<?xml version="1.0" encoding="UTF-8"?>
<resources>
    <string name="Ship">Nave</string>
    <string name="Satellite">Satélite</string>
    <string name="Device">Sistema adicional</string>
    <string name="DroneBay">Bahía de drones</string>
    <string name="Weapon">Arma</string>
    <string name="Armor">Armadura</string>
    <string name="Reactor">Reactor</string>
    <string name="Engine">Motor</string>
    <string name="FuelTank">Tanque de combustible</string>
    <string name="WeightReduction">Reducción de masa</string>
    <string name="DroneBayCapacity">Capacidad</string>
    <string name="DroneBayCooldown">Enfriamiento</string>
    <string name="WeaponType">Arma</string>
    <string name="WeaponSlots">Ranuras de armas</string>
    <string name="CellCount">Tamaño</string>
    <string name="EngineSize">Tamaño de motor</string>
    <string name="Damage">Ataque</string>
    <string name="HitPoints">Puntos de ataque</string>
    <string name="Energy">Energía</string>
    <string name="Shield">Escudo</string>
    <string name="ShieldPoints">Puntos de escudo</string>
    <string name="ShieldRechargeRate">Tasa de recarga</string>
    <string name="ShieldRechargeCooldown">Tiempo de recarga</string>
    <string name="RepairRate">Velocidad de reparación</string>
    <string name="RepairCooldown">Enfriamiento de reparación</string>
    <string name="RechargeRate">Velocidad de recarga</string>
    <string name="RechargeCooldown">Tiempo de recarga</string>
    <string name="Weight">Peso</string>
    <string name="EquipmentWeight">Peso de equipo</string>
    <string name="RamDamage">Daño de embestida</string>
    <string name="DamageAbsorption">Absorción de energía</string>
    <string name="Velocity">Velocidad</string>
    <string name="TurnRate">Velocidad de giro</string>
    <string name="WeaponModifiers">Arma</string>
    <string name="DamageModifier">Daño</string>
    <string name="FireRateModifier">Velocidad de disparo</string>
    <string name="RangeModifier">Alcance de disparo</string>
    <string name="EnergyModifier">Coste de energía</string>
    <string name="DroneDamageModifier">Daños de dron</string>
    <string name="DroneRangeModifier">Alcance de dron</string>
    <string name="DroneSpeedModifier">Velocidad de dron</string>
    <string name="DroneDefenseModifier">Defensa de dron</string>
    <string name="DroneReconstructionTime">Tiempo de construcción de dron</string>
    <string name="KineticDamageResistance">Resistencia cinética</string>
    <string name="ThermalDamageResistance">Resistencia térmica</string>
    <string name="EnergyDamageResistance">Resistencia energética</string>
    <string name="Size">Tamaño</string>
    <string name="EnergyConsumption">Consumo de energía</string>
    <string name="MenuWeapon">Ataque</string>
    <string name="MenuEnergy">Energia</string>
    <string name="MenuDefense">Defensa</string>
    <string name="MenuEngine">Velocidad</string>
    <string name="MenuDrones">Drones</string>
    <string name="MenuSpecial">Especial</string>
    <string name="Exit">Salir</string>
    <string name="AvailableSpace">Espacios libres: $1 / $2</string>
    <string name="MoreInfo">Más información</string>
    <string name="MinEnergy">Encender si hay más de $1% energía</string>
    <string name="Automatic">Automático</string>
    <string name="KeyBinding">Tecla de acción</string>
    <string name="DroneBehaviour">Comportamiento:</string>
    <string name="RequiredCell">Tipo de celda</string>
    <string name="PressToInstall">Arrastrar para instalar</string>
    <string name="NotEnoughSpace">Espacio insuficiente</string>
    <string name="AlreadyInstalled">Este módulo ya está instalado</string>
    <string name="CannotInstall">El módulo no es compatible con esta nave</string>
    <string name="ShowDetails">Mostrar detalles</string>
    <string name="RemoveComponent">Quitar</string>
    <string name="UnlockComponent">Desbloquear</string>
    <string name="UnlockAllComponents">Desbloquear todo</string>
    <string name="UnlockConfirmation">¿Desbloquear el módulo seleccionado?</string>
    <string name="UnlockAllConfirmation">¿Desbloquear todos los módulos bloqueados?</string>
    <string name="RequiredSpaceText">Espacio libre necesario: $1</string>
    <string name="OutOfSpaceWarning">No hay suficiente espacio libre. Liberar $1 ${1|celda|celdas} o subir el nivel de la nave.</string>
    <string name="LowLevelText">Su nave debe ser de nivel $1 o superior.</string>
    <string name="LowLevelUnlockText">Para desbloquear este módulo su nave debe ser de nivel $1 o superior.</string>
    <string name="UnknownTech">Tecnología desconocida. Primero necesitas investigarla.</string>
    <string name="RemoveAllConfirmation">¿Quitar todos los módulos de la nave?</string>
    <string name="WeaponDamage">Daño</string>
    <string name="WeaponDPS">Daños por segundo</string>
    <string name="WeaponRepair">Reparación</string>
    <string name="WeaponRepairPerSec">Reparación por segundo</string>
    <string name="WeaponDamageShield">Daño de escudo</string>
    <string name="WeaponShieldPerSec">Daño de escudo por segundo</string>
    <string name="KineticDamage">Daño cinético</string>
    <string name="KineticDPS">DPS cinético</string>
    <string name="HeatDamage">Daño térmico</string>
    <string name="HeatDPS">DPS térmico</string>
    <string name="EnergyDamage">Daño energético</string>
    <string name="EnergyDPS">DPS energético</string>
    <string name="WeaponEnergy">Consumo de energía</string>
    <string name="WeaponEPS">Energía por segundo</string>
    <string name="WeaponRange">Rango</string>
    <string name="WeaponCooldown">Tiempo de recarga</string>
    <string name="WeaponVelocity">Velocidad</string>
    <string name="WeaponArea">Área de efecto</string>
    <string name="WeaponImpulse">Impulso</string>
    <string name="DamageType">Tipo de daño</string>
    <string name="ImpactDamage">Cinético</string>
    <string name="EnergyDamage">Energía</string>
    <string name="HeatDamage">Calor</string>
    <string name="ShipName">Nombre de nave</string>
    <string name="ClickToInstall">Pulse para instalar</string>
    <string name="ClickToRemove">Pulse para quitar</string>
    <string name="CantBeInstalled">No se puede instalar</string>
    <string name="LeftSide">Puerto</string>
    <string name="RightSide">Estribor</string>
    <string name="LockedSlot">La ranura aún no está disponible. Puedes desbloquearla en el árbol de habilidades.</string>
    <string name="EmptySlot0">Ranura vacía para naves de clase fragata</string>
    <string name="EmptySlot1">Ranura vacía para naves de clase destructor</string>
    <string name="EmptySlot2">Ranura vacío para naves de clase crucero</string>
    <string name="EmptySlot3">Ranura vacía para naves de clase acorazado</string>
    <string name="EmptySlot4">Ranura vacía para naves de clase capital</string>
    <string name="ShipClass">Clase:</string>
    <string name="ClassDrone">Dron</string>
    <string name="ClassFrigate">Fragata</string>
    <string name="ClassDestroyer">Destructor</string>
    <string name="ClassCruiser">Crucero</string>
    <string name="ClassBattleship">Acorazado</string>
    <string name="ClassTitan">Nave capital</string>
    <string name="ClassStarbase">Base estelar</string>
    <string name="GroupAll">Todos los módulos</string>
    <string name="GroupWeapon">Armas</string>
    <string name="GroupArmor">Módulos de defensa</string>
    <string name="GroupEngines">Motores</string>
    <string name="GroupEnergy">Módulos de energía</string>
    <string name="GroupDrones">Drones</string>
    <string name="GroupSpecial">Módulos especiales</string>
    <string name="GroupShip">$1 módulos de nave</string>
    <string name="GroupShips">Naves</string>
    <string name="GroupSatellites">Satélites</string>
    <string name="GroupLeftSatellite">Satélite 1</string>
    <string name="GroupRightSatellite">Satélite 2</string>
    <string name="GroupWeaponAny">Armas para cualquier ranura</string>
    <string name="GroupWeaponC">Armas de proyectiles</string>
    <string name="GroupWeaponL">Armas láser</string>
    <string name="GroupWeaponM">Misiles</string>
    <string name="GroupWeaponT">Torpedos de energía</string>
    <string name="GroupWeaponS">Armas especiales</string>
    <string name="GroupAllItems">Todos los objetos</string>
    <string name="GroupBlueprints">Planos</string>
    <string name="GroupCoins">Monedas</string>
    <string name="BuiltInSystems">Sistemas integrados</string>
    <string name="Improvements">Mejoras</string>
    <string name="ValuePerSecond">$1 / seg</string>
    <string name="None">Ninguno</string>
    <string name="TurretTurnRate">Velocidad de giro de torreta</string>
    <string name="NewPreset">Nuevo preajuste</string>
    <string name="LoadPreset">Cargar</string>
    <string name="SavePreset">Guardar</string>
    <string name="DeletePreset">Eliminar</string>
    <string name="DeletePresetConfirmation">¿Quiere borrar el preajuste seleccionado? Esta operación no se puede deshacer.</string>
    <string name="OverwritePresetConfirmation">¿Quiere sobrescribir el preajuste seleccionado?</string>
    <string name="PartiallyLoadedPreset">El preajuste se ha cargado parcialmente debido a la falta de módulos en el inventario.</string>
</resources>
